{
  "_id": "EZXppKxpmpemOlbT",
  "name": "Arremesso Potente",
  "type": "poder",
  "img": "systems/tormenta20/icons/poderes/combate.webp",
  "effects": [],
  "folder": "Rgbah8U70jOKi5DF",
  "sort": 0,
  "flags": {
    "core": {
      "sourceId": "Compendium.tormenta20.poderes.EZXppKxpmpemOlbT"
    }
  },
  "system": {
    "description": {
      "value": "<p style=\"text-align: justify;\">Quando usa uma arma de arremesso, voc&ecirc; pode usar sua For&ccedil;a em vez de Destreza nos testes de ataque. Se voc&ecirc; possuir o poder Ataque Poderoso, poder&aacute; us&aacute;-lo com armas de arremesso.</p>\n<p style=\"text-align: justify;\"><em>Pr&eacute;-requisitos:</em> For 1, Estilo de Arremesso.</p>",
      "chat": "",
      "unidentified": ""
    },
    "source": "T20, pg. 124 (JdA)",
    "ativacao": {
      "execucao": "",
      "custo": 0,
      "qtd": "",
      "condicao": "",
      "special": ""
    },
    "duracao": {
      "value": 0,
      "units": "",
      "special": ""
    },
    "target": {
      "value": null,
      "width": null,
      "units": "",
      "type": ""
    },
    "range": {
      "value": null,
      "units": ""
    },
    "consume": {
      "type": "",
      "target": "",
      "amount": null,
      "mpMultiplier": false
    },
    "efeito": "",
    "alcance": "none",
    "alvo": "",
    "area": "",
    "resistencia": {
      "pericia": "",
      "atributo": "sab",
      "bonus": 0,
      "txt": ""
    },
    "rolls": [],
    "tipo": "geral",
    "subtipo": "Combate",
    "chatFlavor": "",
    "origin": "",
    "tags": [],
    "chatGif": ""
  },
  "ownership": {
    "default": 0
  },
  "_stats": {
    "systemId": "tormenta20",
    "systemVersion": "1.4.116",
    "coreVersion": "11.298",
    "createdTime": 1664306183830,
    "modifiedTime": 1684630371462,
    "lastModifiedBy": "ZWR5Tn3AhSIFqwp6"
  },
  "_key": "!items!EZXppKxpmpemOlbT"
}
