{
  "name": "Atributos - Dahllan",
  "type": "poder",
  "img": "systems/tormenta20/icons/racas/dahllan.webp",
  "effects": [
    {
      "label": "Atributos - Dahllan",
      "icon": "systems/tormenta20/icons/racas/dahllan.webp",
      "origin": "Item.xtJZYZOg0PVeFbNP",
      "tint": "#FFFFFF",
      "flags": {
        "tormenta20": {
          "onuse": false,
          "durationScene": false
        }
      },
      "duration": {
        "startTime": null,
        "seconds": null,
        "combat": null,
        "rounds": null,
        "turns": null,
        "startRound": null,
        "startTurn": null
      },
      "disabled": false,
      "_id": "vSfyT5e6cGYKSKuD",
      "changes": [
        {
          "key": "system.atributos.sab.value",
          "mode": 2,
          "value": "2",
          "priority": null
        },
        {
          "key": "system.atributos.des.value",
          "mode": 2,
          "value": "1",
          "priority": null
        },
        {
          "key": "system.atributos.int.value",
          "mode": 2,
          "value": "-1",
          "priority": null
        }
      ],
      "transfer": true,
      "_key": "!items.effects!wE9jUJXjq5TxkI2u.vSfyT5e6cGYKSKuD"
    }
  ],
  "flags": {
    "core": {
      "sourceId": "Compendium.tormenta20.poderes.azlQPwLSPLE0hm04"
    }
  },
  "system": {
    "description": {
      "value": "<p>Sabedoria +2, Destreza +1, Intelig&ecirc;ncia -1.</p>",
      "chat": "",
      "unidentified": ""
    },
    "source": "T20, pg. 21 (JdA)",
    "ativacao": {
      "execucao": "move",
      "custo": 0,
      "qtd": "",
      "condicao": "",
      "special": ""
    },
    "duracao": {
      "value": 0,
      "units": "",
      "special": ""
    },
    "target": {
      "value": null,
      "width": null,
      "units": "",
      "type": ""
    },
    "range": {
      "value": null,
      "units": ""
    },
    "consume": {
      "type": "",
      "target": "",
      "amount": null,
      "mpMultiplier": false
    },
    "efeito": "",
    "alcance": "none",
    "alvo": "",
    "area": "",
    "resistencia": {
      "pericia": "",
      "atributo": "sab",
      "bonus": 0,
      "txt": ""
    },
    "rolls": [],
    "tipo": "racial",
    "subtipo": "Dahllan",
    "chatFlavor": "",
    "origin": "",
    "tags": [],
    "chatGif": ""
  },
  "ownership": {
    "default": 0,
    "tIn9sSkrT3mDWirx": 3,
    "jJlhMQyjTGPyLMsV": 3
  },
  "_stats": {
    "systemId": "tormenta20",
    "systemVersion": "1.4.116",
    "coreVersion": "11.298",
    "createdTime": 1664306184739,
    "modifiedTime": 1684630371462,
    "lastModifiedBy": "ZWR5Tn3AhSIFqwp6"
  },
  "folder": "Q99EWrBDNMKWfbCR",
  "sort": 0,
  "_id": "wE9jUJXjq5TxkI2u",
  "_key": "!items!wE9jUJXjq5TxkI2u"
}
